frigate_event_handler/__init__.py
frigate_event_handler/api.py
frigate_event_handler/cli.py
frigate_event_handler/config.py
frigate_event_handler/const.py
frigate_event_handler/daemon.py
frigate_event_handler/exceptions.py
frigate_event_handler/models.py
frigate_event_handler/version.py
frigate_event_handler-0.3.1.dist-info/LICENSE
frigate_event_handler-0.3.1.dist-info/METADATA
frigate_event_handler-0.3.1.dist-info/WHEEL
frigate_event_handler-0.3.1.dist-info/entry_points.txt
frigate_event_handler-0.3.1.dist-info/RECORD
